mseep_python_hello_warp_mcp-0.1.1.dist-info/licenses/LICENSE
python_hello_warp_mcp/__init__.py
python_hello_warp_mcp/__main__.py
python_hello_warp_mcp/server.py
mseep_python_hello_warp_mcp-0.1.1.dist-info/METADATA
mseep_python_hello_warp_mcp-0.1.1.dist-info/WHEEL
mseep_python_hello_warp_mcp-0.1.1.dist-info/entry_points.txt
mseep_python_hello_warp_mcp-0.1.1.dist-info/top_level.txt
mseep_python_hello_warp_mcp-0.1.1.dist-info/RECORD
